flask_menubuilder.py
setup.cfg
setup.py
Flask_MenuBuilder.egg-info/PKG-INFO
Flask_MenuBuilder.egg-info/SOURCES.txt
Flask_MenuBuilder.egg-info/dependency_links.txt
Flask_MenuBuilder.egg-info/not-zip-safe
Flask_MenuBuilder.egg-info/requires.txt
Flask_MenuBuilder.egg-info/top_level.txt