Metadata-Version: 1.1
Name: Flask-MenuBuilder
Version: 0.9.2
Summary: An easy way to create menus to use with flask.
Home-page: http://dev.ufsoft.org/projects/menu-builder
Author: Pedro Algarvio
Author-email: pedro@algarvio.me
License: BSD
Platform: any
Classifier: Environment :: Web Environment
Classifier: Intended Audience :: Developers
Classifier: License :: OSI Approved :: BSD License
Classifier: Operating System :: OS Independent
Classifier: Programming Language :: Python
Classifier: Topic :: Internet :: WWW/HTTP :: Dynamic Content
Classifier: Topic :: Software Development :: Libraries :: Python Modules
